palworld_server_launcher/__init__.py
palworld_server_launcher/main.py
palworld_server_launcher/templates/palserver.rules.template
palworld_server_launcher/templates/palserver.service.template
palworld_server_launcher-0.1.19.dist-info/licenses/LICENSE
palworld_server_launcher-0.1.19.dist-info/METADATA
palworld_server_launcher-0.1.19.dist-info/WHEEL
palworld_server_launcher-0.1.19.dist-info/entry_points.txt
palworld_server_launcher-0.1.19.dist-info/top_level.txt
palworld_server_launcher-0.1.19.dist-info/RECORD
