Metadata-Version: 2.4
Name: palworld-server-launcher
Version: 0.1.19
Summary: A simple tool to install and manage a Palworld dedicated server on Linux.
Author-email: axatbhardwaj <axatbhardwaj@gmail.com>
License-Expression: MIT
Classifier: Programming Language :: Python :: 3
Classifier: Operating System :: POSIX :: Linux
Requires-Python: >=3.8
License-File: LICENSE
Requires-Dist: typer
Requires-Dist: rich
Dynamic: license-file
